lzhfile/__init__.py
lzhfile/core.py
lzhfile/filebase.py
lzhfile/types/excel.py
lzhfile/types/ini.py
lzhfile/types/json.py
lzhfile/types/math.py
lzhfile/types/nfo.py
lzhfile/types/pdf.py
lzhfile/types/pkl.py
lzhfile/types/suffix.py
lzhfile/types/txt.py
lzhlog/__init__.py
lzhlog/ftimer.py
lzhnet/__init__.py
lzhnet/chrome.py
lzhnet/mail.py
lzhnet/ssh.py
lzhprt/__init__.py
lzhprt/_base.py
lzhprt/_tool.py
lzhprt/container.py
lzhprt/pchunk.py
lzhprt/pdiy.py
lzhprt/unit.py
lzhsta/__init__.py
lzhsta/fit.py
lzhsta/para.py
lzhsys/__init__.py
lzhsys/process.py
lzhpy-1.0.2.dist-info/METADATA
lzhpy-1.0.2.dist-info/WHEEL
lzhpy-1.0.2.dist-info/top_level.txt
lzhpy-1.0.2.dist-info/RECORD
